{
  "shadow": {
    "hud": {
      "$type": "shadow",
      "$value": [
        {
          "offsetX": "0px",
          "offsetY": "5px",
          "blur": "17px",
          "spread": "0px",
          "color": "rgba(0, 0, 0, 0.2)"
        },
        {
          "offsetX": "0px",
          "offsetY": "2px",
          "blur": "7px",
          "spread": "0px",
          "color": "rgba(0, 0, 0, 0.15)"
        }
      ]
    },
    "floatingWindow": {
      "$type": "shadow",
      "$value": {
        "offsetX": "0px",
        "offsetY": "2px",
        "blur": "14px",
        "spread": "0px",
        "color": "rgba(0, 0, 0, 0.15)"
      }
    }
  },
  "elevation": {
    "100Canvas": {
      "$type": "shadow",
      "$value": [
        {
          "offsetX": "0px",
          "offsetY": "0px",
          "blur": "0.5px",
          "spread": "0px",
          "color": "rgba(0, 0, 0, 0.5)"
        },
        {
          "offsetX": "0px",
          "offsetY": "1px",
          "blur": "3px",
          "spread": "0px",
          "color": "rgba(0, 0, 0, 0.4)"
        },
        {
          "offsetX": "0px",
          "offsetY": "1px",
          "blur": "0px",
          "spread": "0px",
          "color": "rgba(255, 255, 255, 0.1)",
          "inset": true
        },
        {
          "offsetX": "0px",
          "offsetY": "0px",
          "blur": "1px",
          "spread": "0px",
          "color": "rgba(255, 255, 255, 0.3)",
          "inset": true
        }
      ]
    },
    "200Canvas": {
      "$type": "shadow",
      "$value": [
        {
          "offsetX": "0px",
          "offsetY": "3px",
          "blur": "8px",
          "spread": "0px",
          "color": "rgba(0, 0, 0, 0.35)"
        },
        {
          "offsetX": "0px",
          "offsetY": "1px",
          "blur": "3px",
          "spread": "0px",
          "color": "rgba(0, 0, 0, 0.5)"
        },
        {
          "offsetX": "0px",
          "offsetY": "1px",
          "blur": "0px",
          "spread": "0px",
          "color": "rgba(255, 255, 255, 0.08)",
          "inset": true
        },
        {
          "offsetX": "0px",
          "offsetY": "0px",
          "blur": "1px",
          "spread": "0px",
          "color": "rgba(255, 255, 255, 0.3)",
          "inset": true
        }
      ]
    },
    "300Tooltip": {
      "$type": "shadow",
      "$value": [
        {
          "offsetX": "0px",
          "offsetY": "5px",
          "blur": "12px",
          "spread": "0px",
          "color": "rgba(0, 0, 0, 0.35)"
        },
        {
          "offsetX": "0px",
          "offsetY": "1px",
          "blur": "3px",
          "spread": "0px",
          "color": "rgba(0, 0, 0, 0.5)"
        },
        {
          "offsetX": "0px",
          "offsetY": "1px",
          "blur": "0px",
          "spread": "0px",
          "color": "rgba(255, 255, 255, 0.08)",
          "inset": true
        },
        {
          "offsetX": "0px",
          "offsetY": "0px",
          "blur": "1px",
          "spread": "0px",
          "color": "rgba(255, 255, 255, 0.3)",
          "inset": true
        }
      ]
    },
    "400MenuPanel": {
      "$type": "shadow",
      "$value": [
        {
          "offsetX": "0px",
          "offsetY": "10px",
          "blur": "16px",
          "spread": "0px",
          "color": "rgba(0, 0, 0, 0.35)"
        },
        {
          "offsetX": "0px",
          "offsetY": "2px",
          "blur": "5px",
          "spread": "0px",
          "color": "rgba(0, 0, 0, 0.35)"
        },
        {
          "offsetX": "0px",
          "offsetY": "1px",
          "blur": "0px",
          "spread": "0px",
          "color": "rgba(255, 255, 255, 0.08)",
          "inset": true
        },
        {
          "offsetX": "0px",
          "offsetY": "0px",
          "blur": "1px",
          "spread": "0px",
          "color": "rgba(255, 255, 255, 0.35)",
          "inset": true
        }
      ]
    },
    "500ModalWindow": {
      "$type": "shadow",
      "$value": [
        {
          "offsetX": "0px",
          "offsetY": "10px",
          "blur": "24px",
          "spread": "0px",
          "color": "rgba(0, 0, 0, 0.45)"
        },
        {
          "offsetX": "0px",
          "offsetY": "3px",
          "blur": "5px",
          "spread": "0px",
          "color": "rgba(0, 0, 0, 0.35)"
        },
        {
          "offsetX": "0px",
          "offsetY": "1px",
          "blur": "0px",
          "spread": "0px",
          "color": "rgba(255, 255, 255, 0.08)",
          "inset": true
        },
        {
          "offsetX": "0px",
          "offsetY": "0px",
          "blur": "1px",
          "spread": "0px",
          "color": "rgba(255, 255, 255, 0.35)",
          "inset": true
        }
      ]
    }
  }
}
